README.rst
setup.py
./greyhound/__init__.py
./greyhound/box.py
./greyhound/main.py
./greyhound/resource.py
./greyhound/server.py
./greyhound/util.py
greyhound.egg-info/PKG-INFO
greyhound.egg-info/SOURCES.txt
greyhound.egg-info/dependency_links.txt
greyhound.egg-info/entry_points.txt
greyhound.egg-info/not-zip-safe
greyhound.egg-info/requires.txt
greyhound.egg-info/top_level.txt