Metadata-Version: 1.1
Name: greyhound
Version: 0.0.2
Summary: Convenience API for interacting with Greyhound point cloud web services
Home-page: http://greyhound.io
Author: Howard Butler
Author-email: howard@hobu.co
License: BSD
Keywords: point clouds,LiDAR
Platform: UNKNOWN
Classifier: Development Status :: 4 - Beta
Classifier: Intended Audience :: Developers
Classifier: Intended Audience :: Information Technology
Classifier: Intended Audience :: Science/Research
Classifier: License :: OSI Approved :: BSD License
Classifier: Programming Language :: Python :: 2.7
Classifier: Programming Language :: Python :: 3.5
Classifier: Programming Language :: Python :: 2
Classifier: Programming Language :: Python :: 3
Classifier: Topic :: Multimedia :: Graphics :: Graphics Conversion
Classifier: Topic :: Scientific/Engineering :: GIS
